wsipre/__init__.py
wsipre/annotation.py
wsipre/show.py
wsipre/slide.py
wsipre/tissue.py
wsipre-0.1.2.dist-info/LICENSE
wsipre-0.1.2.dist-info/METADATA
wsipre-0.1.2.dist-info/WHEEL
wsipre-0.1.2.dist-info/top_level.txt
wsipre-0.1.2.dist-info/RECORD
