Metadata-Version: 2.1
Name: wsipre
Version: 0.1.2
Summary: Whole-slide image preprocessing
Home-page: https://github.com/luisvalesilva/wsipre
Author: Luis A. Vale Silva
Author-email: luisvalesilva@gmail.com
License: BSD
Keywords: whole-slide image virtual slide OpenSlide machine learning deep learning
Platform: UNKNOWN
Classifier: Programming Language :: Python :: 3
Classifier: License :: OSI Approved :: MIT License
Classifier: Operating System :: OS Independent
